{
  "main": {
    "id": "07476b9917a72541",
    "type": "split",
    "children": [
      {
        "id": "fc965dac643cfc8b",
        "type": "tabs",
        "children": [
          {
            "id": "a7f159e73dbf6623",
            "type": "leaf",
            "state": {
              "type": "markdown",
              "state": {
                "file": "Git/ssh/Генерация нового SSH-ключа и добавление его в ssh-agent.md",
                "mode": "source",
                "source": false
              }
            }
          }
        ]
      }
    ],
    "direction": "vertical"
  },
  "left": {
    "id": "8b4246bb5d3165a9",
    "type": "split",
    "children": [
      {
        "id": "044c2ed1dfd9f54d",
        "type": "tabs",
        "children": [
          {
            "id": "ae122010be15f045",
            "type": "leaf",
            "state": {
              "type": "file-explorer",
              "state": {
                "sortOrder": "alphabetical"
              }
            }
          },
          {
            "id": "8d6416cbc9f5d0a9",
            "type": "leaf",
            "state": {
              "type": "search",
              "state": {
                "query": "",
                "matchingCase": false,
                "explainSearch": false,
                "collapseAll": false,
                "extraContext": false,
                "sortOrder": "alphabetical"
              }
            }
          },
          {
            "id": "321af204ba62d0da",
            "type": "leaf",
            "state": {
              "type": "starred",
              "state": {}
            }
          },
          {
            "id": "360d2465aaa631eb",
            "type": "leaf",
            "state": {
              "type": "bookmarks",
              "state": {}
            }
          }
        ]
      }
    ],
    "direction": "horizontal",
    "width": 300
  },
  "right": {
    "id": "3040105c8497142a",
    "type": "split",
    "children": [
      {
        "id": "fbb3bffa065ab60a",
        "type": "tabs",
        "children": [
          {
            "id": "9efbb90b662c56c4",
            "type": "leaf",
            "state": {
              "type": "backlink",
              "state": {
                "file": "Git/ssh/Генерация нового SSH-ключа и добавление его в ssh-agent.md",
                "collapseAll": false,
                "extraContext": false,
                "sortOrder": "alphabetical",
                "showSearch": false,
                "searchQuery": "",
                "backlinkCollapsed": false,
                "unlinkedCollapsed": true
              }
            }
          },
          {
            "id": "6d431d8f5a6b4894",
            "type": "leaf",
            "state": {
              "type": "outgoing-link",
              "state": {
                "file": "Git/ssh/Генерация нового SSH-ключа и добавление его в ssh-agent.md",
                "linksCollapsed": false,
                "unlinkedCollapsed": true
              }
            }
          },
          {
            "id": "9a22b14c276a2905",
            "type": "leaf",
            "state": {
              "type": "tag",
              "state": {
                "sortOrder": "frequency",
                "useHierarchy": true
              }
            }
          },
          {
            "id": "cce627de5804a9a3",
            "type": "leaf",
            "state": {
              "type": "outline",
              "state": {
                "file": "Git/ssh/Генерация нового SSH-ключа и добавление его в ssh-agent.md"
              }
            }
          }
        ]
      }
    ],
    "direction": "horizontal",
    "width": 300,
    "collapsed": true
  },
  "left-ribbon": {
    "hiddenItems": {
      "switcher:Меню быстрого перехода": false,
      "graph:Граф": false,
      "canvas:Создать новый холст": false,
      "daily-notes:Сегодняшняя заметка": false,
      "templates:Вставить шаблон": false,
      "command-palette:Открыть палитру команд": false
    }
  },
  "active": "a7f159e73dbf6623",
  "lastOpenFiles": [
    "Python/Заметки по учебе/Матрицы.md",
    "image.png",
    "Python/Django/Модели данных/Создание модели данных.md",
    "Python/Заметки по учебе",
    "Python/Django/Создание приложения.md",
    "Python/Django/Модели данных",
    "Python/Django/Без названия.md",
    "Python/Django/Запуск сервера.md",
    "Python/Django/Установка.md",
    "Python/Django/settings.py.md",
    "Python/Django/Команды.md",
    "Python/Django/Миграция.md",
    "Python/Django/Подключение BD.md",
    "DB/postgresql/Команды.md",
    "Obsidian/#Синтаксис.md",
    "DB/postgresql",
    "DB",
    "SQL",
    "NODE/stream.md",
    "NODE/Export and Import.md",
    "NODE/http.md",
    "NODE/ES6.md",
    "NODE/Начало.md",
    "SVG/сайты.md",
    "TS/ts object.md",
    "React/Пакеты/Без названия.md",
    "Docker/Команды/ps.md",
    "Docker/Команды/info.md",
    "Docker/Команды/images.md",
    "Docker/Команды/docker.md",
    "Git/ssh/проверка существующих ключей.md",
    "NODE/Debug",
    "Python/Tests/pytest",
    "Python/Tests",
    "NewsLine.png",
    "CSS",
    "css/Псевдоклассы",
    "Pasted image 20230323194709.png",
    "Pasted image 20230323114316.png",
    "Pasted image 20230323090506.png"
  ]
}